setup.py
Distribution_HSM/Binomialdistribution.py
Distribution_HSM/Binomialdistribution1.py
Distribution_HSM/Gaussiandistribution.py
Distribution_HSM/Generaldistribution.py
Distribution_HSM/__init__.py
Distribution_HSM.egg-info/PKG-INFO
Distribution_HSM.egg-info/SOURCES.txt
Distribution_HSM.egg-info/dependency_links.txt
Distribution_HSM.egg-info/not-zip-safe
Distribution_HSM.egg-info/top_level.txt