Metadata-Version: 1.0
Name: Distribution-HSM
Version: 0.2
Summary: distributions
Home-page: UNKNOWN
Author: Hrushikesh Mulavekar
Author-email: hmulavekar@gmail.com
License: UNKNOWN
Platform: UNKNOWN
